somenzz/__init__.py
somenzz/db/__init__.py
somenzz/db/database_client.py
somenzz/db/database_interface.py
somenzz/db/db2_client.py
somenzz/db/mysql_client.py
somenzz/db/postgres_client.py
somenzz/db/utils.py
somenzz_db-0.1.dist-info/METADATA
somenzz_db-0.1.dist-info/WHEEL
somenzz_db-0.1.dist-info/top_level.txt
somenzz_db-0.1.dist-info/RECORD
