Metadata-Version: 2.1
Name: somenzz-db
Version: 0.1
Summary: database interface
Home-page: https://github.com/somenzz/db
Author: somenzz
Author-email: UNKNOWN
License: UNKNOWN
Platform: UNKNOWN
